<?xml version="1.0" encoding="utf-8"?>
<LinearLayout xmlns:android="http://schemas.android.com/apk/res-auto" app:orientation="vertical" app:id="@a$f/uyz" app:background="@color/ls" app:layout_width="match_parent" app:layout_height="match_parent">
    <ScrollView app:id="@id/atq" app:layout_width="match_parent" app:layout_height="UNKNOWN_DATA_0x1" app:fillViewport="true" app:layout_weight="1.0">
        <LinearLayout app:orientation="vertical" app:id="@id/atr" app:paddingTop="0dp" app:layout_width="match_parent" app:layout_height="wrap_content" style="@style/t2">
            <TextView app:id="@a$f/uyx" app:visibility="gone" app:text="@string/du2" app:drawableLeft="@drawable/a_j" app:drawablePadding="7dp" style="@style/te" />
            <TextView app:id="@a$f/uys" app:text="@string/dt3" style="@style/te" />
            <com.tencent.mm.wallet_core.ui.formview.WalletFormView app:id="@a$f/uyq" app:titleText="@string/dtn" app:contentHint="@a$i/uQz" style="@style/t0" />
            <TextView app:id="@a$f/uyr" app:text="@a$i/uQj" style="@style/th" />
            <TextView app:id="@a$f/uyk" app:text="@a$i/uQc" style="@style/te" />
            <com.tencent.mm.wallet_core.ui.formview.WalletFormView app:id="@a$f/uyy" app:titleText="@string/dse" app:contentHint="@string/dvr" style="@style/ft" />
            <TextView app:textColor="#888888" app:id="@a$f/uyo" app:visibility="gone" style="@style/th" />
            <TextView app:textColor="#888888" app:id="@a$f/uyl" style="@style/th" />
            <TextView app:id="@a$f/uyn" app:text="@string/dsm" style="@style/te" />
            <LinearLayout style="@style/tt">
                <com.tencent.mm.wallet_core.ui.formview.WalletFormView app:id="@a$f/uja" app:imeOptions="actionNone|actionSearch|actionSend|actionNext|actionDone|actionPrevious" app:titleText="@string/dsl" app:contentHint="@string/dsk" style="@style/tb" />
                <com.tencent.mm.wallet_core.ui.formview.WalletFormView app:id="@a$f/ujb" app:titleText="@string/dss" app:contentHint="@string/dsn" style="@style/tc" />
            </LinearLayout>
            <TextView app:id="@a$f/uym" app:text="@a$i/uQg" style="@style/th" />
            <TextView app:id="@a$f/uyu" app:text="@string/dt_" style="@style/te" />
            <LinearLayout style="@style/tt">
                <com.tencent.mm.wallet_core.ui.formview.WalletFormView app:id="@a$f/urM" app:titleText="@string/dub" app:contentHint="@a$i/uQE" style="@style/tu" />
                <com.tencent.mm.wallet_core.ui.formview.WalletFormView app:id="@a$f/uyH" app:titleText="@a$i/uQf" app:contentHint="@string/dsh" style="@style/ft" />
                <com.tencent.mm.wallet_core.ui.formview.WalletFormView app:id="@a$f/ukS" app:imeOptions="actionNone|actionSearch|actionSend|actionNext|actionDone|actionPrevious" app:titleText="@string/dt9" app:contentHint="@string/dt6" style="@style/tl" />
            </LinearLayout>
            <TextView app:id="@a$f/uyw" app:text="@string/du0" style="@style/te" />
            <LinearLayout style="@style/tt">
                <com.tencent.mm.wallet_core.ui.formview.WalletFormView app:id="@a$f/utG" app:titleText="@string/dtz" app:contentHint="@string/dty" style="@style/ft" />
                <com.tencent.mm.wallet_core.ui.formview.WalletFormView app:id="@a$f/utF" app:titleText="@string/dtx" app:contentHint="@string/dtw" style="@style/ft" />
            </LinearLayout>
            <com.tencent.mm.wallet_core.ui.formview.WalletFormView app:id="@a$f/urD" app:layout_marginTop="@dimen/h5" app:imeOptions="actionNone|actionSearch|actionSend|actionNext|actionDone|actionPrevious" app:titleText="@string/dtg" app:contentHint="@a$i/uQu" style="@style/tr" />
            <TextView app:id="@a$f/uyt" app:visibility="visible" app:text="@a$i/uQq" style="@style/th" />
            <TextView app:id="@a$f/uyi" app:text="@string/dsd" style="@style/te" />
            <LinearLayout style="@style/tt">
                <com.tencent.mm.wallet_core.ui.formview.WalletFormView app:id="@a$f/ukI" app:imeOptions="actionNone|actionSearch|actionSend|actionNext|actionDone|actionPrevious" app:titleText="@string/dt0" app:contentHint="@string/dsz" style="@style/ei" />
                <com.tencent.mm.wallet_core.ui.formview.WalletFormView app:id="@a$f/uls" app:imeOptions="actionNone|actionSearch|actionSend|actionNext|actionDone|actionPrevious" app:titleText="@string/dte" app:contentHint="@string/dtd" style="@style/ei" />
                <com.tencent.mm.wallet_core.ui.formview.WalletFormView app:id="@a$f/ueG" app:imeOptions="actionNone|actionSearch|actionSend|actionNext|actionDone|actionPrevious" app:titleText="@string/ds9" app:contentHint="@string/ds8" style="@style/ft" />
                <com.tencent.mm.wallet_core.ui.formview.WalletFormView app:id="@a$f/ueu" app:imeOptions="actionNone|actionSearch|actionSend|actionNext|actionDone|actionPrevious" app:maxLength="90" app:titleText="@string/ds3" app:contentHint="@string/ds2" style="@style/ei" />
                <com.tencent.mm.wallet_core.ui.formview.WalletFormView app:id="@a$f/utw" app:imeOptions="actionNone|actionSearch|actionSend|actionNext|actionDone|actionPrevious" app:titleText="@string/dtt" app:contentHint="@string/dtp" style="@style/tx" />
                <com.tencent.mm.wallet_core.ui.formview.WalletFormView app:id="@a$f/utD" app:imeOptions="actionNone|actionSearch|actionSend|actionNext|actionDone|actionPrevious" app:titleText="@string/dtv" app:contentHint="@string/dtu" style="@style/ei" />
                <com.tencent.mm.wallet_core.ui.formview.WalletFormView app:id="@a$f/ujX" app:imeOptions="actionNone|actionSearch|actionSend|actionNext|actionDone|actionPrevious" app:titleText="@string/dsu" app:contentHint="@string/dst" style="@style/tf" />
            </LinearLayout>
            <TextView app:id="@a$f/uyh" app:text="@string/dsv" style="@style/th" />
            <LinearLayout app:gravity="left|right|center_horizontal|fill_horizontal|center|fill|start|end" app:orientation="horizontal" app:layout_marginLeft="@dimen/jb" app:layout_marginTop="@dimen/h5" app:layout_marginRight="@dimen/jb" style="@style/l0">
                <CheckBox app:textSize="@dimen/gu" app:textColor="@color/bp" app:gravity="top|bottom|left|right|center_vertical|fill_vertical|center_horizontal|fill_horizontal|center|fill|start|end" app:layout_gravity="top|bottom|left|right|center_vertical|fill_vertical|center_horizontal|fill_horizontal|center|fill|start|end" app:id="@a$f/uex" app:clickable="true" app:layout_width="wrap_content" app:layout_height="wrap_content" app:checked="true" app:minHeight="22dp" app:text="@a$i/uQH" style="@style/me" />
                <Button app:textSize="@dimen/gu" app:textColor="@a$c/ubw" app:ellipsize="marquee" app:gravity="top|bottom|left|right|center_vertical|fill_vertical|center_horizontal|fill_horizontal|center|fill|start|end" app:layout_gravity="top|bottom|left|right|center_vertical|fill_vertical|center_horizontal|fill_horizontal|center|fill|start|end" app:id="@id/ccx" app:paddingTop="5dp" app:paddingRight="0dp" app:paddingBottom="5dp" app:layout_marginLeft="0dp" app:minHeight="30dp" app:text="@string/duc" app:singleLine="true" style="@style/tk" />
            </LinearLayout>
            <CheckBox app:textSize="@dimen/gu" app:textColor="@color/bp" app:gravity="top|bottom|left|right|center_vertical|fill_vertical|center_horizontal|fill_horizontal|center|fill|start|end" app:layout_gravity="top|bottom|left|right|center_vertical|fill_vertical|center_horizontal|fill_horizontal|center|fill|start|end" app:id="@a$f/uev" app:background="0x0" app:paddingLeft="24dp" app:clickable="true" app:layout_width="wrap_content" app:layout_height="wrap_content" app:layout_marginTop="@dimen/iu" app:checked="true" app:minHeight="22dp" app:drawableLeft="@a$d/qfl" app:drawablePadding="8dp" style="@style/t8" />
            <Button app:id="@id/ak_" app:layout_width="match_parent" app:layout_height="wrap_content" app:layout_marginTop="3dp" app:layout_marginBottom="38dp" app:text="@l/dFQ" style="@style/tq" />
            <TextView app:layout_gravity="top|bottom|center_vertical|fill_vertical|center|fill" app:id="@a$f/uzT" app:paddingTop="5dp" app:layout_height="match_parent" app:layout_margin="0dp" style="@style/ty" />
        </LinearLayout>
    </ScrollView>
    <include app:visibility="gone" app:layout_width="match_parent" app:layout_height="wrap_content" layout="@layout/aj_" />
</LinearLayout>
